pycountrycode/__init__.py
pycountrycode/countryData.txt
pycountrycode/country_data.py
pycountrycode/countrycode.py
pycountrycode-1.1.8.dist-info/LICENSE
pycountrycode-1.1.8.dist-info/METADATA
pycountrycode-1.1.8.dist-info/WHEEL
pycountrycode-1.1.8.dist-info/top_level.txt
pycountrycode-1.1.8.dist-info/RECORD
