Metadata-Version: 2.1
Name: pycountrycode
Version: 1.1.8
Summary: A neat country call code retriever
Home-page: https://github.com/xeroxzen/country-code
Author: Andile Jaden Mbele
Author-email: andilembele020@gmail.com
License: MIT
Classifier: License :: OSI Approved :: MIT License
Classifier: Programming Language :: Python :: 3
Classifier: Programming Language :: Python :: 3.8
Classifier: Programming Language :: Python :: 3.9
Classifier: Programming Language :: Python :: 3.10
Classifier: Programming Language :: Python :: 3.11
License-File: LICENSE
